odoo/addons/sale_order_margin_percent/README.rst
odoo/addons/sale_order_margin_percent/__init__.py
odoo/addons/sale_order_margin_percent/__manifest__.py
odoo/addons/sale_order_margin_percent/i18n/ca.po
odoo/addons/sale_order_margin_percent/i18n/de.po
odoo/addons/sale_order_margin_percent/i18n/el_GR.po
odoo/addons/sale_order_margin_percent/i18n/es.po
odoo/addons/sale_order_margin_percent/i18n/es_ES.po
odoo/addons/sale_order_margin_percent/i18n/es_VE.po
odoo/addons/sale_order_margin_percent/i18n/fi.po
odoo/addons/sale_order_margin_percent/i18n/fr.po
odoo/addons/sale_order_margin_percent/i18n/hr.po
odoo/addons/sale_order_margin_percent/i18n/hr_HR.po
odoo/addons/sale_order_margin_percent/i18n/hu.po
odoo/addons/sale_order_margin_percent/i18n/it.po
odoo/addons/sale_order_margin_percent/i18n/nl.po
odoo/addons/sale_order_margin_percent/i18n/nl_NL.po
odoo/addons/sale_order_margin_percent/i18n/pt.po
odoo/addons/sale_order_margin_percent/i18n/pt_BR.po
odoo/addons/sale_order_margin_percent/i18n/ro.po
odoo/addons/sale_order_margin_percent/i18n/sale_order_margin_percent.pot
odoo/addons/sale_order_margin_percent/i18n/sk.po
odoo/addons/sale_order_margin_percent/i18n/sl.po
odoo/addons/sale_order_margin_percent/i18n/tr.po
odoo/addons/sale_order_margin_percent/i18n/tr_TR.po
odoo/addons/sale_order_margin_percent/i18n/vi_VN.po
odoo/addons/sale_order_margin_percent/i18n/zh_CN.po
odoo/addons/sale_order_margin_percent/models/__init__.py
odoo/addons/sale_order_margin_percent/models/sale_order_margin.py
odoo/addons/sale_order_margin_percent/readme/CONTRIBUTORS.rst
odoo/addons/sale_order_margin_percent/readme/DESCRIPTION.rst
odoo/addons/sale_order_margin_percent/readme/USAGE.rst
odoo/addons/sale_order_margin_percent/static/description/icon.png
odoo/addons/sale_order_margin_percent/static/description/index.html
odoo/addons/sale_order_margin_percent/tests/__init__.py
odoo/addons/sale_order_margin_percent/tests/test_margin_percent.py
odoo12_addon_sale_order_margin_percent-12.0.1.1.1.dist-info/METADATA
odoo12_addon_sale_order_margin_percent-12.0.1.1.1.dist-info/WHEEL
odoo12_addon_sale_order_margin_percent-12.0.1.1.1.dist-info/top_level.txt
odoo12_addon_sale_order_margin_percent-12.0.1.1.1.dist-info/RECORD
