Metadata-Version: 2.1
Name: odoo12-addon-sale-order-margin-percent
Version: 12.0.1.1.1
Summary: Show Percent in sale order
Home-page: https://github.com/OCA/margin-analysis
Author: PESOL, Odoo Community Association (OCA)
Author-email: support@odoo-community.org
License: AGPL-3
Platform: UNKNOWN
Classifier: Programming Language :: Python
Classifier: Framework :: Odoo
Classifier: Framework :: Odoo :: 12.0
Classifier: License :: OSI Approved :: GNU Affero General Public License v3
Requires-Python: >=3.5
Requires-Dist: odoo (<12.1dev,>=12.0a)
